trackalpaca/__init__.py
trackalpaca/example.py
trackalpaca/tracker.py
trackalpaca-0.2.dist-info/METADATA
trackalpaca-0.2.dist-info/WHEEL
trackalpaca-0.2.dist-info/top_level.txt
trackalpaca-0.2.dist-info/RECORD
