Metadata-Version: 2.4
Name: TrackAlpaca
Version: 0.2
Summary: A Metric Tracking and Visualization Tool
Home-page: https://github.com/RazielMoesch/TrackAlpaca
Author: Raziel Moesch
Author-email: razielmoeschwork@gmail.com
Classifier: Programming Language :: Python :: 3
Classifier: License :: OSI Approved :: MIT License
Classifier: Operating System :: OS Independent
Requires-Python: >=3.9
Requires-Dist: matplotlib
Requires-Dist: pillow
Dynamic: author
Dynamic: author-email
Dynamic: classifier
Dynamic: description
Dynamic: description-content-type
Dynamic: home-page
Dynamic: requires-dist
Dynamic: requires-python
Dynamic: summary
